pychroot/__init__.py
pychroot/_verinfo.py
pychroot/base.py
pychroot/exceptions.py
pychroot/utils.py
pychroot/__pycache__/__init__.cpython-38.pyc
pychroot/__pycache__/_verinfo.cpython-38.pyc
pychroot/__pycache__/base.cpython-38.pyc
pychroot/__pycache__/exceptions.cpython-38.pyc
pychroot/__pycache__/utils.cpython-38.pyc
pychroot/scripts/__init__.py
pychroot/scripts/pychroot.py
pychroot/scripts/__pycache__/__init__.cpython-38.pyc
pychroot/scripts/__pycache__/pychroot.cpython-38.pyc
pychroot-0.10.4.data/scripts/pychroot
pychroot-0.10.4.dist-info/LICENSE
pychroot-0.10.4.dist-info/METADATA
pychroot-0.10.4.dist-info/WHEEL
pychroot-0.10.4.dist-info/top_level.txt
pychroot-0.10.4.dist-info/RECORD
