Metadata-Version: 2.1
Name: pychroot
Version: 0.10.4
Summary: a python library and cli tool that simplify chroot handling
Home-page: https://github.com/pkgcore/pychroot
Author: Tim Harder
Author-email: radhermit@gmail.com
License: BSD
Platform: Posix
Classifier: Intended Audience :: Developers
Classifier: License :: OSI Approved :: BSD License
Classifier: Programming Language :: Python :: 3.8
Classifier: Programming Language :: Python :: 3.9
Requires-Dist: snakeoil (~=0.8.9)
